olca2tidas/cli.py
olca2tidas/converter.py
olca2tidas-0.1.6.dist-info/METADATA
olca2tidas-0.1.6.dist-info/WHEEL
olca2tidas-0.1.6.dist-info/entry_points.txt
olca2tidas-0.1.6.dist-info/licenses/LICENSE
olca2tidas-0.1.6.dist-info/RECORD
