Metadata-Version: 2.4
Name: olca2tidas
Version: 0.1.6
Summary: Convert openLCA JSON-LD to TIDAS/eILCD JSON for TianGong LCA database
Project-URL: Homepage, https://github.com/Kirin-Ciao/olca2tidas
Project-URL: Repository, https://github.com/Kirin-Ciao/olca2tidas
Author: Qilin Cao
License: MIT
License-File: LICENSE
Keywords: ILCD,LCA,TIDAS,TianGong,converter,openLCA
Requires-Python: >=3.9
